konnekt/HTTPClient.py
konnekt/__init__.py
konnekt-0.0.4.dist-info/METADATA
konnekt-0.0.4.dist-info/WHEEL
konnekt-0.0.4.dist-info/top_level.txt
konnekt-0.0.4.dist-info/RECORD
