Metadata-Version: 2.1
Name: konnekt
Version: 0.0.4
Summary: Sending API request via internet
Author: Alok Solanky
Author-email: pbadgly@gmail.com
Keywords: python,send,request,get put post delete,internet,sockets
Classifier: Development Status :: 1 - Planning
Classifier: Intended Audience :: Developers
Classifier: Programming Language :: Python :: 3
Classifier: Operating System :: Unix
Classifier: Operating System :: MacOS :: MacOS X
Classifier: Operating System :: Microsoft :: Windows
